pyvroom-1.14.0.dist-info/RECORD
pyvroom-1.14.0.dist-info/LICENSE
pyvroom-1.14.0.dist-info/WHEEL
pyvroom-1.14.0.dist-info/entry_points.txt
pyvroom-1.14.0.dist-info/top_level.txt
pyvroom-1.14.0.dist-info/METADATA
vroom/break_.py
vroom/amount.py
vroom/time_window.py
vroom/job.py
vroom/_vroom.cpython-311-darwin.so
vroom/vehicle.py
vroom/__init__.py
vroom/location.py
vroom/input/vehicle_step.py
vroom/input/forced_service.py
vroom/input/__init__.py
vroom/input/input.py
vroom/solution/solution.py
vroom/solution/__init__.py
vroom/.dylibs/libstdc++.6.dylib
vroom/.dylibs/libssl.1.1.dylib
vroom/.dylibs/libcrypto.1.1.dylib
vroom/.dylibs/libgcc_s.1.1.dylib
